{"tag":{"__typename":"TagEntityResponse","data":{"__typename":"TagEntity","id":"20","attributes":{"__typename":"Tag","name":"Resistir","images":{"__typename":"ImageRelationResponseCollection","data":[{"__typename":"ImageEntity","id":"36","attributes":{"__typename":"Image","file":{"__typename":"UploadFileRelationResponseCollection","data":[{"__typename":"UploadFileEntity","id":"110","attributes":{"__typename":"UploadFile","url":"https://res.cloudinary.com/crea-lo/image/upload/v1687102184/Resistir_5b645841d3.jpg"}}]}}}]},"videos":{"__typename":"VideoRelationResponseCollection","data":[]},"creations":{"__typename":"CreationRelationResponseCollection","data":[]},"next":{"__typename":"TagEntityResponse","data":{"__typename":"TagEntity","id":"21"}},"previous":{"__typename":"TagEntityResponse","data":{"__typename":"TagEntity","id":"19"}}}}}}